sqlian/__init__.py
sqlian/base.py
sqlian/compat.py
sqlian/databases.py
sqlian/engines.py
sqlian/records.py
sqlian/utils.py
sqlian/mysql/__init__.py
sqlian/mysql/clauses.py
sqlian/mysql/databases.py
sqlian/mysql/engines.py
sqlian/mysql/statements.py
sqlian/postgresql/__init__.py
sqlian/postgresql/clauses.py
sqlian/postgresql/databases.py
sqlian/postgresql/engines.py
sqlian/postgresql/statements.py
sqlian/sqlite/__init__.py
sqlian/sqlite/databases.py
sqlian/sqlite/engines.py
sqlian/standard/__init__.py
sqlian/standard/clauses.py
sqlian/standard/compositions.py
sqlian/standard/constants.py
sqlian/standard/databases.py
sqlian/standard/engines.py
sqlian/standard/expressions.py
sqlian/standard/functions.py
sqlian/standard/statements.py
sqlian-0.1.0.dev0.dist-info/DESCRIPTION.rst
sqlian-0.1.0.dev0.dist-info/METADATA
sqlian-0.1.0.dev0.dist-info/RECORD
sqlian-0.1.0.dev0.dist-info/WHEEL
sqlian-0.1.0.dev0.dist-info/metadata.json
sqlian-0.1.0.dev0.dist-info/top_level.txt
